stoat/Array.py
stoat/BaseStructure.py
stoat/BaseTypeFactory.py
stoat/CStructure.py
stoat/CompoundByte.py
stoat/MetaStructure.py
stoat/Structure.py
stoat/TypeFactory.py
stoat/__init__.py
stoat-0.0.1.dist-info/LICENSE
stoat-0.0.1.dist-info/METADATA
stoat-0.0.1.dist-info/WHEEL
stoat-0.0.1.dist-info/top_level.txt
stoat-0.0.1.dist-info/RECORD
